<?xml version="1.0" encoding="utf-8" ?>
<dwsync>
<file name="fondo_body.png" server="C:/wamp/www/siai/" local="129979826040000000" remote="129979826040000000" />
<file name="fondo_identidad.png" server="C:/wamp/www/siai/" local="129979814680000000" remote="129979814680000000" />
<file name="logo.png" server="C:/wamp/www/siai/" local="129979811840000000" remote="129979811840000000" />
<file name="logo_politecnica.png" server="C:/wamp/www/siai/" local="129979813020000000" remote="129979813020000000" />
<file name="fondo_navegacion.png" server="C:/wamp/www/siai/" local="129980151460000000" remote="129980151460000000" />
<file name="fondo_principal.png" server="C:/wamp/www/siai/" local="129980155140000000" remote="129980155140000000" />
<file name="btn_siguiente.png" server="C:/wamp/www/siai/" local="129997066800000000" remote="129997066800000000" />
<file name="btn_siguiente_active.png" server="C:/wamp/www/siai/" local="129997074780000000" remote="129997074780000000" />
</dwsync>